odoo/addons/stock_quant_package_dimension_total_weight_from_packaging/README.rst
odoo/addons/stock_quant_package_dimension_total_weight_from_packaging/__init__.py
odoo/addons/stock_quant_package_dimension_total_weight_from_packaging/__manifest__.py
odoo/addons/stock_quant_package_dimension_total_weight_from_packaging/i18n/es.po
odoo/addons/stock_quant_package_dimension_total_weight_from_packaging/i18n/fr.po
odoo/addons/stock_quant_package_dimension_total_weight_from_packaging/i18n/it.po
odoo/addons/stock_quant_package_dimension_total_weight_from_packaging/i18n/stock_quant_package_dimension_total_weight_from_packaging.pot
odoo/addons/stock_quant_package_dimension_total_weight_from_packaging/models/__init__.py
odoo/addons/stock_quant_package_dimension_total_weight_from_packaging/models/stock_quant_package.py
odoo/addons/stock_quant_package_dimension_total_weight_from_packaging/readme/CONTRIBUTORS.rst
odoo/addons/stock_quant_package_dimension_total_weight_from_packaging/readme/CREDITS.rst
odoo/addons/stock_quant_package_dimension_total_weight_from_packaging/readme/DESCRIPTION.rst
odoo/addons/stock_quant_package_dimension_total_weight_from_packaging/static/description/icon.png
odoo/addons/stock_quant_package_dimension_total_weight_from_packaging/static/description/index.html
odoo/addons/stock_quant_package_dimension_total_weight_from_packaging/tests/__init__.py
odoo/addons/stock_quant_package_dimension_total_weight_from_packaging/tests/test_package_weight.py
odoo_addon_stock_quant_package_dimension_total_weight_from_packaging-16.0.1.0.0.7.dist-info/METADATA
odoo_addon_stock_quant_package_dimension_total_weight_from_packaging-16.0.1.0.0.7.dist-info/WHEEL
odoo_addon_stock_quant_package_dimension_total_weight_from_packaging-16.0.1.0.0.7.dist-info/top_level.txt
odoo_addon_stock_quant_package_dimension_total_weight_from_packaging-16.0.1.0.0.7.dist-info/RECORD
