Metadata-Version: 2.1
Name: odoo-addon-stock_quant_package_dimension_total_weight_from_packaging
Version: 16.0.1.0.0.7
Summary: Estimated weight of a package
Home-page: https://github.com/OCA/stock-logistics-workflow
Author: Camptocamp, Odoo Community Association (OCA)
Author-email: support@odoo-community.org
License: AGPL-3
Classifier: Programming Language :: Python
Classifier: Framework :: Odoo
Classifier: Framework :: Odoo :: 16.0
Classifier: License :: OSI Approved :: GNU Affero General Public License v3
Classifier: Development Status :: 3 - Alpha
Requires-Python: >=3.10
Requires-Dist: odoo-addon-product-total-weight-from-packaging<16.1dev,>=16.0dev
Requires-Dist: odoo-addon-stock-quant-package-dimension<16.1dev,>=16.0dev
Requires-Dist: odoo<16.1dev,>=16.0a
